rfdocgen/__init__.py
rfdocgen/create_docs.py
rfdocgen/main.py
rfdocgen/server/__init__.py
rfdocgen/server/docs.py
rfdocgen/server/static/bootstrap.min.css
rfdocgen/server/static/rflib.css
rfdocgen/server/static/rflib.min.js
rfdocgen/server/static/rftest.css
rfdocgen/server/static/rftest.min.js
rfdocgen/server/templates/base.html
rfdocgen/server/templates/breadcrumbs.html
rfdocgen/server/templates/docs_index.html
rfdocgen/server/templates/docs_tree.html
rfdocgen/server/templates/rflib_file.html
rfdocgen/server/templates/rftest_file.html
rfdocgen-0.0.10.dist-info/LICENSE.md
rfdocgen-0.0.10.dist-info/METADATA
rfdocgen-0.0.10.dist-info/WHEEL
rfdocgen-0.0.10.dist-info/top_level.txt
rfdocgen-0.0.10.dist-info/RECORD
